argser/__init__.py
argser/__main__.py
argser/consts.py
argser/display.py
argser/docstring.py
argser/exceptions.py
argser/fields.py
argser/formatters.py
argser/logging.py
argser/parse_func.py
argser/parser.py
argser/utils.py
argser-0.0.16.dist-info/entry_points.txt
argser-0.0.16.dist-info/WHEEL
argser-0.0.16.dist-info/METADATA
argser-0.0.16.dist-info/RECORD
