Metadata-Version: 2.1
Name: argser
Version: 0.0.16
Summary: Arguments parsing without boilerplate.
Home-page: https://github.com/vanyakosmos/argser
License: MIT
Keywords: flags,argparse
Author: Bachynin Ivan
Author-email: bachynin.i@gmail.com
Requires-Python: >=3.6,<4.0
Classifier: Development Status :: 3 - Alpha
Classifier: Intended Audience :: Developers
Classifier: License :: OSI Approved :: MIT License
Classifier: Programming Language :: Python :: 3
Classifier: Programming Language :: Python :: 3.6
Classifier: Programming Language :: Python :: 3.7
Classifier: Programming Language :: Python :: 3.8
Classifier: Topic :: Utilities
Provides-Extra: all
Provides-Extra: argcomplete
Provides-Extra: tabulate
Requires-Dist: argcomplete (>=1.10,<2.0); extra == "argcomplete" or extra == "all"
Requires-Dist: tabulate (>=0.8.5,<0.9.0); extra == "tabulate" or extra == "all"
Requires-Dist: termcolor (>=1.1,<2.0)
Project-URL: Documentation, https://argser.readthedocs.io/en/stable
Project-URL: Repository, https://github.com/vanyakosmos/argser
